rvid/tex_runner/__init__.py
rvid/tex_runner/__version__.py
rvid/tex_runner/external_resources.py
rvid/tex_runner/latex.py
rvid/tex_runner/py.typed
rvid.tex_runner-0.2.0.dist-info/METADATA
rvid.tex_runner-0.2.0.dist-info/WHEEL
rvid.tex_runner-0.2.0.dist-info/top_level.txt
rvid.tex_runner-0.2.0.dist-info/RECORD
