Metadata-Version: 2.1
Name: rvid.tex-runner
Version: 0.2.0
Summary: Utility functions for rendering XeLaTeX documents from Python
Author-email: Arvid Müllern-Aspegren <kontakt@rvid.se>
Project-URL: homepage, https://hg.sr.ht/~rvid/rvid.tex-runner
Requires-Python: >=3.11
Provides-Extra: dev
Requires-Dist: black ; extra == 'dev'
Requires-Dist: mypy[reports] ; extra == 'dev'
Requires-Dist: isort ; extra == 'dev'
